{
  "project_info": {
    "project_number": "262220095299",
    "project_id": "green-coffee-bean-system",
    "storage_bucket": "green-coffee-bean-system.firebasestorage.app"
  },
  "client": [
    {
      "client_info": {
        "mobilesdk_app_id": "1:262220095299:android:7580285dbaae0a5a1259f6",
        "android_client_info": {
          "package_name": "Green.coffeebean"
        }
      },
      "oauth_client": [],
      "api_key": [
        {
          "current_key": "AIzaSyDv1VJWuVAlz--QDNk5CWZKdOUNWTrgwD8"
        }
      ],
      "services": {
        "appinvite_service": {
          "other_platform_oauth_client": []
        }
      }
    }
  ],
  "configuration_version": "1"
}